karq/__init__.py
karq/core.py
karq/exceptions.py
karq/main.py
karq/retry.py
karq/utils.py
karq-0.0.1.dist-info/METADATA
karq-0.0.1.dist-info/WHEEL
karq-0.0.1.dist-info/top_level.txt
karq-0.0.1.dist-info/RECORD
